pulp_python/__init__.py
pulp_python/pytest_plugin.py
pulp_python/app/__init__.py
pulp_python/app/global_access_conditions.py
pulp_python/app/modelresource.py
pulp_python/app/models.py
pulp_python/app/provenance.py
pulp_python/app/replica.py
pulp_python/app/serializers.py
pulp_python/app/settings.py
pulp_python/app/urls.py
pulp_python/app/utils.py
pulp_python/app/viewsets.py
pulp_python/app/management/__init__.py
pulp_python/app/management/commands/__init__.py
pulp_python/app/management/commands/repair-python-metadata.py
pulp_python/app/migrations/0001_initial.py
pulp_python/app/migrations/0001_squashed_0010_update_json_field.py
pulp_python/app/migrations/0002_pythonpackagecontent_python_version.py
pulp_python/app/migrations/0003_new_sync_filters.py
pulp_python/app/migrations/0004_DATA_swap_distribution_model.py
pulp_python/app/migrations/0005_pythonpackagecontent_sha256.py
pulp_python/app/migrations/0006_pythonrepository_autopublish.py
pulp_python/app/migrations/0007_pythonpackagecontent_mv-2-1.py
pulp_python/app/migrations/0008_pythonpackagecontent_unique_sha256.py
pulp_python/app/migrations/0009_pythondistribution_allow_uploads.py
pulp_python/app/migrations/0010_update_json_field.py
pulp_python/app/migrations/0011_alter_pythondistribution_distribution_ptr_and_more.py
pulp_python/app/migrations/0012_add_domain.py
pulp_python/app/migrations/0013_add_rbac_permissions.py
pulp_python/app/migrations/0014_pythonpackagecontent_dynamic_and_more.py
pulp_python/app/migrations/0015_alter_pythonpackagecontent_options.py
pulp_python/app/migrations/0016_pythonpackagecontent_metadata_sha256.py
pulp_python/app/migrations/0017_pythonpackagecontent_size.py
pulp_python/app/migrations/0018_packageprovenance.py
pulp_python/app/migrations/0019_create_missing_metadata_artifacts.py
pulp_python/app/migrations/__init__.py
pulp_python/app/pypi/__init__.py
pulp_python/app/pypi/serializers.py
pulp_python/app/pypi/views.py
pulp_python/app/tasks/__init__.py
pulp_python/app/tasks/publish.py
pulp_python-3.23.0.dist-info/licenses/LICENSE
pulp_python-3.23.0.dist-info/METADATA
pulp_python-3.23.0.dist-info/WHEEL
pulp_python-3.23.0.dist-info/entry_points.txt
pulp_python-3.23.0.dist-info/top_level.txt
pulp_python-3.23.0.dist-info/RECORD
